[    
    {
        "Name": "카스테라주",
        "Desc": "자신의 보유 체력의 50%를 채워준다.(체력 50일때 +25)",
        "Type": 2,
        "Atk": 0,
        "Def": 0,
        "Hp": 0,
        "Price": 150,
        "IsEquipped": false,
        "IsPurchased": false,
		"Value": 0.5,
		"Qty": 0
    },
	{
        "Name": "복분자주",
        "Desc": "정읍의 자랑, 최대체력의 50%를 체력회복한다.",
        "Type": 2,
        "Atk": 0,
        "Def": 0,
        "Hp": 0,
        "Price": 350,
        "IsEquipped": false,
        "IsPurchased": false,
		"Value": 0.5,
		"Qty": 0
    },
	{
        "Name": "조니왔다",
        "Desc": "유명 위스키, 최대체력의 100%를 체력회복한다.",
        "Type": 2,
        "Atk": 0,
        "Def": 0,
        "Hp": 0,
        "Price": 550,
        "IsEquipped": false,
        "IsPurchased": false,
		"Value": 1,
		"Qty": 0
    }
]